bitbucket_helper-0.1.7.data/scripts/bitbucket-helper
helperlib/__init__.py
helperlib/bitbucket/__init__.py
helperlib/bitbucket/bitbucket_api.py
helperlib/git/__init__.py
helperlib/git/git_cli.py
bitbucket_helper-0.1.7.dist-info/METADATA
bitbucket_helper-0.1.7.dist-info/WHEEL
bitbucket_helper-0.1.7.dist-info/top_level.txt
bitbucket_helper-0.1.7.dist-info/RECORD
