Metadata-Version: 2.1
Name: bitbucket-helper
Version: 0.1.7
Summary: A bitbucket server helper for working with lots of repos.
Home-page: https://github.com/omahoco/bitbucket-helper
Author: Cormac O'Mahony
Author-email: cormac@omahony.id.au
License: UNKNOWN
Platform: UNKNOWN
Classifier: Programming Language :: Python :: 3
Classifier: License :: OSI Approved :: MIT License
Classifier: Operating System :: OS Independent
Requires-Python: >=3.7
Requires-Dist: stashy (>=0.6)
Requires-Dist: pybitbucket37 (>=0.0.2)
Requires-Dist: PyInquirer (>=1.0.3)
